Metadata-Version: 1.2
Name: DKAN-client
Version: 0.1.1
Summary: Client for DKAN
Home-page: UNKNOWN
Author: Konrad Wölms
Author-email: konrad.woelms@gmail.com
License: UNKNOWN
Platform: UNKNOWN
Requires-Python: >=3.6
